<?xml version="1.0" encoding="UTF-8"?><record_update table="catalog_ui_policy_action">
    <catalog_ui_policy_action action="INSERT_OR_UPDATE">
        <catalog_item/>
        <catalog_variable>IO:a1f235211b62a5908c5143f3cc4bcbfb</catalog_variable>
        <cleared>false</cleared>
        <disabled>ignore</disabled>
        <field/>
        <mandatory>false</mandatory>
        <order>100</order>
        <sys_class_name>catalog_ui_policy_action</sys_class_name>
        <sys_created_by>Terry.Lillo</sys_created_by>
        <sys_created_on>2023-07-28 14:20:42</sys_created_on>
        <sys_id>fbef31311b10759062e50ed2cd4bcb0d</sys_id>
        <sys_mod_count>4</sys_mod_count>
        <sys_name>location</sys_name>
        <sys_package display_value="Cellular Device Ordering" source="ddd5ad831b3ba5d08c5143f3cc4bcb61">ddd5ad831b3ba5d08c5143f3cc4bcb61</sys_package>
        <sys_policy/>
        <sys_scope display_value="CDW Ordering Integration">4630a8861ba9851062e50ed2cd4bcb61</sys_scope>
        <sys_update_name>catalog_ui_policy_action_fbef31311b10759062e50ed2cd4bcb0d</sys_update_name>
        <sys_updated_by>Terry.Lillo</sys_updated_by>
        <sys_updated_on>2023-11-15 20:38:19</sys_updated_on>
        <table/>
        <ui_policy display_value="Location not found is true - s">cfdf7dfd1bdc359062e50ed2cd4bcbac</ui_policy>
        <variable>location</variable>
        <variable_set display_value="Delivery Information">7eadc3b71b926d508c5143f3cc4bcb57</variable_set>
        <visible>false</visible>
    </catalog_ui_policy_action>
    <sys_claim action="INSERT_OR_UPDATE">
        <claim_owner_scope display_value="CDW Ordering Integration">4630a8861ba9851062e50ed2cd4bcb61</claim_owner_scope>
        <claim_timestamp>18bd4b4c7020000001</claim_timestamp>
        <metadata_update_name>catalog_ui_policy_action_fbef31311b10759062e50ed2cd4bcb0d</metadata_update_name>
        <previous_claim_app_version>2.2.3</previous_claim_app_version>
        <previous_claim_name>CDW Ordering Integration</previous_claim_name>
        <previous_claim_scope>4630a8861ba9851062e50ed2cd4bcb61</previous_claim_scope>
        <sys_created_by>Terry.Lillo</sys_created_by>
        <sys_created_on>2023-11-15 20:38:19</sys_created_on>
        <sys_id>4245fdd51beabd5062e50ed2cd4bcb25</sys_id>
        <sys_mod_count>0</sys_mod_count>
        <sys_updated_by>Terry.Lillo</sys_updated_by>
        <sys_updated_on>2023-11-15 20:38:19</sys_updated_on>
    </sys_claim>
    <sys_claim action="INSERT_OR_UPDATE">
        <claim_owner_scope display_value="CDW Ordering Integration">4630a8861ba9851062e50ed2cd4bcb61</claim_owner_scope>
        <claim_timestamp>18bd4b4c6f80000001</claim_timestamp>
        <metadata_update_name>catalog_ui_policy_action_fbef31311b10759062e50ed2cd4bcb0d</metadata_update_name>
        <previous_claim_app_version>1.0.7</previous_claim_app_version>
        <previous_claim_name>Cellular Device Ordering</previous_claim_name>
        <previous_claim_scope>ddd5ad831b3ba5d08c5143f3cc4bcb61</previous_claim_scope>
        <sys_created_by>Terry.Lillo</sys_created_by>
        <sys_created_on>2023-11-15 20:38:19</sys_created_on>
        <sys_id>0645fdd51beabd5062e50ed2cd4bcb25</sys_id>
        <sys_mod_count>0</sys_mod_count>
        <sys_updated_by>Terry.Lillo</sys_updated_by>
        <sys_updated_on>2023-11-15 20:38:19</sys_updated_on>
    </sys_claim>
</record_update>
