<?xml version="1.0" encoding="UTF-8"?><record_update sys_domain="global" table="pa_m2m_dashboard_tabs">
    <pa_m2m_dashboard_tabs action="INSERT_OR_UPDATE">
        <dashboard display_value="ServiceNow Admin Dashboard">50e780211b6a15108c5143f3cc4bcb65</dashboard>
        <home>false</home>
        <homepage/>
        <order>1</order>
        <sys_class_name>pa_m2m_dashboard_tabs</sys_class_name>
        <sys_created_by>Terry.Lillo</sys_created_by>
        <sys_created_on>2022-10-14 14:56:46</sys_created_on>
        <sys_domain>global</sys_domain>
        <sys_domain_path>/</sys_domain_path>
        <sys_id>58f740211b6a15108c5143f3cc4bcb61</sys_id>
        <sys_mod_count>0</sys_mod_count>
        <sys_name>50e780211b6a15108c5143f3cc4bcb65</sys_name>
        <sys_overrides/>
        <sys_package display_value="CDW Ordering Integration" source="4630a8861ba9851062e50ed2cd4bcb61">4630a8861ba9851062e50ed2cd4bcb61</sys_package>
        <sys_policy/>
        <sys_scope display_value="CDW Ordering Integration">4630a8861ba9851062e50ed2cd4bcb61</sys_scope>
        <sys_update_name>pa_m2m_dashboard_tabs_58f740211b6a15108c5143f3cc4bcb61</sys_update_name>
        <sys_updated_by>Terry.Lillo</sys_updated_by>
        <sys_updated_on>2022-10-14 21:29:16</sys_updated_on>
        <tab display_value="ServiceNow Admin Das - New Tab">d8f740211b6a15108c5143f3cc4bcb5e</tab>
    </pa_m2m_dashboard_tabs>
</record_update>
